{"nodes": [{"id": "c_users_admin_onedrive_desktop_projects_hostel_backend_apps_payments_admin_py", "label": "admin.py", "file_type": "code", "source_file": "C:\\Users\\admin\\OneDrive\\Desktop\\Projects\\hostel\\backend\\apps\\payments\\admin.py", "source_location": "L1"}], "edges": [{"source": "c_users_admin_onedrive_desktop_projects_hostel_backend_apps_payments_admin_py", "target": "django_contrib", "relation": "imports_from", "context": "import", "confidence": "EXTRACTED", "source_file": "C:\\Users\\admin\\OneDrive\\Desktop\\Projects\\hostel\\backend\\apps\\payments\\admin.py", "source_location": "L1", "weight": 1.0}], "raw_calls": []}